<?xml version='1.0' encoding='utf-8'?>
<TextureAtlas imagePath="startup.png"><SubTexture name="startup yes0000" x="0" y="0" width="1284" height="724" frameX="0" frameY="0" frameWidth="1284" frameHeight="724" />
<SubTexture name="startup yes0001" x="1284" y="0" width="1284" height="724" frameX="0" frameY="0" frameWidth="1284" frameHeight="724" />
<SubTexture name="startup yes0002" x="2568" y="0" width="1284" height="724" frameX="0" frameY="0" frameWidth="1284" frameHeight="724" />
<SubTexture name="startup yes0003" x="3852" y="0" width="1284" height="724" frameX="0" frameY="0" frameWidth="1284" frameHeight="724" />
<SubTexture name="startup yes0004" x="5136" y="0" width="1284" height="724" frameX="0" frameY="0" frameWidth="1284" frameHeight="724" />
<SubTexture name="startup yes0005" x="6420" y="0" width="1284" height="724" frameX="0" frameY="0" frameWidth="1284" frameHeight="724" />
<SubTexture name="startup yes0006" x="7704" y="0" width="1284" height="724" frameX="0" frameY="0" frameWidth="1284" frameHeight="724" />
<SubTexture name="startup yes0007" x="8988" y="0" width="1284" height="724" frameX="0" frameY="0" frameWidth="1284" frameHeight="724" />
<SubTexture name="startup yes0008" x="10272" y="0" width="1284" height="724" frameX="0" frameY="0" frameWidth="1284" frameHeight="724" />
<SubTexture name="startup yes0009" x="11556" y="0" width="1284" height="724" frameX="0" frameY="0" frameWidth="1284" frameHeight="724" />
<SubTexture name="startup yes0010" x="12840" y="0" width="1284" height="724" frameX="0" frameY="0" frameWidth="1284" frameHeight="724" />
<SubTexture name="startup yes0011" x="0" y="724" width="1284" height="724" frameX="0" frameY="0" frameWidth="1284" frameHeight="724" />
<SubTexture name="startup yes0012" x="1284" y="724" width="1284" height="724" frameX="0" frameY="0" frameWidth="1284" frameHeight="724" />
<SubTexture name="startup yes0013" x="2568" y="724" width="1284" height="724" frameX="0" frameY="0" frameWidth="1284" frameHeight="724" />
<SubTexture name="startup yes0014" x="3852" y="724" width="1284" height="724" frameX="0" frameY="0" frameWidth="1284" frameHeight="724" />
<SubTexture name="startup yes0015" x="5136" y="724" width="1284" height="724" frameX="0" frameY="0" frameWidth="1284" frameHeight="724" />
<SubTexture name="startup yes0016" x="6420" y="724" width="1284" height="724" frameX="0" frameY="0" frameWidth="1284" frameHeight="724" />
<SubTexture name="startup yes0017" x="7704" y="724" width="1284" height="724" frameX="0" frameY="0" frameWidth="1284" frameHeight="724" />
<SubTexture name="startup yes0018" x="8988" y="724" width="1284" height="724" frameX="0" frameY="0" frameWidth="1284" frameHeight="724" />
<SubTexture name="startup yes0019" x="10272" y="724" width="1284" height="724" frameX="0" frameY="0" frameWidth="1284" frameHeight="724" />
<SubTexture name="startup yes0020" x="11556" y="724" width="1284" height="724" frameX="0" frameY="0" frameWidth="1284" frameHeight="724" />
<SubTexture name="startup yes0021" x="12840" y="724" width="1284" height="724" frameX="0" frameY="0" frameWidth="1284" frameHeight="724" />
<SubTexture name="startup yes0022" x="0" y="1448" width="1284" height="724" frameX="0" frameY="0" frameWidth="1284" frameHeight="724" />
<SubTexture name="startup yes0023" x="1284" y="1448" width="1284" height="724" frameX="0" frameY="0" frameWidth="1284" frameHeight="724" />
<SubTexture name="startup yes0024" x="2568" y="1448" width="1284" height="724" frameX="0" frameY="0" frameWidth="1284" frameHeight="724" />
<SubTexture name="startup yes0025" x="3852" y="1448" width="1284" height="724" frameX="0" frameY="0" frameWidth="1284" frameHeight="724" />
<SubTexture name="startup yes0026" x="5136" y="1448" width="1284" height="724" frameX="0" frameY="0" frameWidth="1284" frameHeight="724" />
<SubTexture name="startup yes0027" x="6420" y="1448" width="1284" height="724" frameX="0" frameY="0" frameWidth="1284" frameHeight="724" />
<SubTexture name="startup yes0028" x="7704" y="1448" width="1284" height="724" frameX="0" frameY="0" frameWidth="1284" frameHeight="724" />
<SubTexture name="startup yes0029" x="8988" y="1448" width="1284" height="724" frameX="0" frameY="0" frameWidth="1284" frameHeight="724" />
<SubTexture name="startup yes0030" x="10272" y="1448" width="1284" height="724" frameX="0" frameY="0" frameWidth="1284" frameHeight="724" />
<SubTexture name="startup yes0031" x="11556" y="1448" width="1284" height="724" frameX="0" frameY="0" frameWidth="1284" frameHeight="724" />
<SubTexture name="startup yes0032" x="12840" y="1448" width="1284" height="724" frameX="0" frameY="0" frameWidth="1284" frameHeight="724" />
<SubTexture name="startup yes0033" x="0" y="2172" width="1284" height="724" frameX="0" frameY="0" frameWidth="1284" frameHeight="724" />
<SubTexture name="startup yes0034" x="1284" y="2172" width="1284" height="724" frameX="0" frameY="0" frameWidth="1284" frameHeight="724" />
<SubTexture name="startup yes0035" x="2568" y="2172" width="1284" height="724" frameX="0" frameY="0" frameWidth="1284" frameHeight="724" />
<SubTexture name="startup yes0036" x="3852" y="2172" width="1284" height="724" frameX="0" frameY="0" frameWidth="1284" frameHeight="724" />
<SubTexture name="startup yes0037" x="5136" y="2172" width="1284" height="724" frameX="0" frameY="0" frameWidth="1284" frameHeight="724" />
<SubTexture name="startup yes0038" x="6420" y="2172" width="1284" height="724" frameX="0" frameY="0" frameWidth="1284" frameHeight="724" />
<SubTexture name="startup yes0039" x="7704" y="2172" width="1284" height="724" frameX="0" frameY="0" frameWidth="1284" frameHeight="724" />
<SubTexture name="startup yes0040" x="8988" y="2172" width="1284" height="724" frameX="0" frameY="0" frameWidth="1284" frameHeight="724" />
<SubTexture name="startup yes0041" x="10272" y="2172" width="1284" height="724" frameX="0" frameY="0" frameWidth="1284" frameHeight="724" />
<SubTexture name="startup yes0042" x="11556" y="2172" width="1284" height="724" frameX="0" frameY="0" frameWidth="1284" frameHeight="724" />
<SubTexture name="startup yes0043" x="12840" y="2172" width="1284" height="724" frameX="0" frameY="0" frameWidth="1284" frameHeight="724" />
<SubTexture name="startup yes0044" x="0" y="2896" width="1284" height="724" frameX="0" frameY="0" frameWidth="1284" frameHeight="724" />
<SubTexture name="startup yes0045" x="1284" y="2896" width="1284" height="724" frameX="0" frameY="0" frameWidth="1284" frameHeight="724" />
<SubTexture name="startup yes0046" x="2568" y="2896" width="1284" height="724" frameX="0" frameY="0" frameWidth="1284" frameHeight="724" />
<SubTexture name="startup yes0047" x="3852" y="2896" width="1284" height="724" frameX="0" frameY="0" frameWidth="1284" frameHeight="724" />
<SubTexture name="startup yes0048" x="5136" y="2896" width="1284" height="724" frameX="0" frameY="0" frameWidth="1284" frameHeight="724" />
<SubTexture name="startup yes0049" x="6420" y="2896" width="1284" height="724" frameX="0" frameY="0" frameWidth="1284" frameHeight="724" />
<SubTexture name="startup yes0050" x="7704" y="2896" width="1284" height="724" frameX="0" frameY="0" frameWidth="1284" frameHeight="724" />
<SubTexture name="startup yes0051" x="8988" y="2896" width="1284" height="724" frameX="0" frameY="0" frameWidth="1284" frameHeight="724" />
<SubTexture name="startup yes0052" x="10272" y="2896" width="1284" height="724" frameX="0" frameY="0" frameWidth="1284" frameHeight="724" />
<SubTexture name="startup yes0053" x="11556" y="2896" width="1284" height="724" frameX="0" frameY="0" frameWidth="1284" frameHeight="724" />
<SubTexture name="startup yes0054" x="12840" y="2896" width="1284" height="724" frameX="0" frameY="0" frameWidth="1284" frameHeight="724" />
<SubTexture name="startup yes0055" x="0" y="3620" width="1284" height="724" frameX="0" frameY="0" frameWidth="1284" frameHeight="724" />
<SubTexture name="startup yes0056" x="1284" y="3620" width="1284" height="724" frameX="0" frameY="0" frameWidth="1284" frameHeight="724" />
<SubTexture name="startup yes0057" x="2568" y="3620" width="1284" height="724" frameX="0" frameY="0" frameWidth="1284" frameHeight="724" />
<SubTexture name="startup yes0058" x="3852" y="3620" width="1284" height="724" frameX="0" frameY="0" frameWidth="1284" frameHeight="724" />
<SubTexture name="startup yes0059" x="5136" y="3620" width="1284" height="724" frameX="0" frameY="0" frameWidth="1284" frameHeight="724" />
<SubTexture name="startup yes0060" x="6420" y="3620" width="1284" height="724" frameX="0" frameY="0" frameWidth="1284" frameHeight="724" />
<SubTexture name="startup yes0061" x="7704" y="3620" width="1284" height="724" frameX="0" frameY="0" frameWidth="1284" frameHeight="724" />
<SubTexture name="startup yes0062" x="8988" y="3620" width="1284" height="724" frameX="0" frameY="0" frameWidth="1284" frameHeight="724" />
<SubTexture name="startup yes0063" x="10272" y="3620" width="1284" height="724" frameX="0" frameY="0" frameWidth="1284" frameHeight="724" />
<SubTexture name="startup yes0064" x="11556" y="3620" width="1284" height="724" frameX="0" frameY="0" frameWidth="1284" frameHeight="724" />
<SubTexture name="startup yes0065" x="12840" y="3620" width="1284" height="724" frameX="0" frameY="0" frameWidth="1284" frameHeight="724" />
<SubTexture name="startup yes0066" x="0" y="4344" width="1284" height="724" frameX="0" frameY="0" frameWidth="1284" frameHeight="724" />
<SubTexture name="startup yes0067" x="1284" y="4344" width="1284" height="724" frameX="0" frameY="0" frameWidth="1284" frameHeight="724" />
<SubTexture name="startup yes0068" x="2568" y="4344" width="1284" height="724" frameX="0" frameY="0" frameWidth="1284" frameHeight="724" />
<SubTexture name="startup yes0069" x="3852" y="4344" width="1284" height="724" frameX="0" frameY="0" frameWidth="1284" frameHeight="724" />
<SubTexture name="startup yes0070" x="5136" y="4344" width="1284" height="724" frameX="0" frameY="0" frameWidth="1284" frameHeight="724" />
<SubTexture name="startup yes0071" x="6420" y="4344" width="1284" height="724" frameX="0" frameY="0" frameWidth="1284" frameHeight="724" />
<SubTexture name="startup yes0072" x="7704" y="4344" width="1284" height="724" frameX="0" frameY="0" frameWidth="1284" frameHeight="724" />
<SubTexture name="startup yes0073" x="8988" y="4344" width="1284" height="724" frameX="0" frameY="0" frameWidth="1284" frameHeight="724" />
<SubTexture name="startup yes0074" x="10272" y="4344" width="1284" height="724" frameX="0" frameY="0" frameWidth="1284" frameHeight="724" />
<SubTexture name="startup yes0075" x="11556" y="4344" width="1284" height="724" frameX="0" frameY="0" frameWidth="1284" frameHeight="724" />
<SubTexture name="startup yes0076" x="12840" y="4344" width="1284" height="724" frameX="0" frameY="0" frameWidth="1284" frameHeight="724" />
<SubTexture name="startup yes0077" x="0" y="5068" width="1284" height="724" frameX="0" frameY="0" frameWidth="1284" frameHeight="724" />
<SubTexture name="startup yes0078" x="1284" y="5068" width="1284" height="724" frameX="0" frameY="0" frameWidth="1284" frameHeight="724" />
<SubTexture name="startup yes0079" x="2568" y="5068" width="1284" height="724" frameX="0" frameY="0" frameWidth="1284" frameHeight="724" />
<SubTexture name="startup yes0080" x="3852" y="5068" width="1284" height="724" frameX="0" frameY="0" frameWidth="1284" frameHeight="724" />
<SubTexture name="startup yes0081" x="5136" y="5068" width="1284" height="724" frameX="0" frameY="0" frameWidth="1284" frameHeight="724" />
<SubTexture name="startup yes0082" x="6420" y="5068" width="1284" height="724" frameX="0" frameY="0" frameWidth="1284" frameHeight="724" />
<SubTexture name="startup yes0083" x="7704" y="5068" width="1284" height="724" frameX="0" frameY="0" frameWidth="1284" frameHeight="724" />
<SubTexture name="startup yes0084" x="8988" y="5068" width="1284" height="724" frameX="0" frameY="0" frameWidth="1284" frameHeight="724" />
<SubTexture name="startup yes0085" x="10272" y="5068" width="1284" height="724" frameX="0" frameY="0" frameWidth="1284" frameHeight="724" />
<SubTexture name="startup yes0086" x="11556" y="5068" width="1284" height="724" frameX="0" frameY="0" frameWidth="1284" frameHeight="724" />
<SubTexture name="startup yes0087" x="12840" y="5068" width="1284" height="724" frameX="0" frameY="0" frameWidth="1284" frameHeight="724" />
<SubTexture name="startup yes0088" x="0" y="5792" width="1284" height="724" frameX="0" frameY="0" frameWidth="1284" frameHeight="724" />
<SubTexture name="startup yes0089" x="1284" y="5792" width="1284" height="724" frameX="0" frameY="0" frameWidth="1284" frameHeight="724" />
<SubTexture name="startup yes0090" x="2568" y="5792" width="1284" height="724" frameX="0" frameY="0" frameWidth="1284" frameHeight="724" />
<SubTexture name="startup yes0091" x="3852" y="5792" width="1284" height="724" frameX="0" frameY="0" frameWidth="1284" frameHeight="724" />
<SubTexture name="startup yes0092" x="5136" y="5792" width="1284" height="724" frameX="0" frameY="0" frameWidth="1284" frameHeight="724" />
<SubTexture name="startup yes0093" x="6420" y="5792" width="1284" height="724" frameX="0" frameY="0" frameWidth="1284" frameHeight="724" />
<SubTexture name="startup yes0094" x="7704" y="5792" width="1284" height="724" frameX="0" frameY="0" frameWidth="1284" frameHeight="724" />
<SubTexture name="startup yes0095" x="8988" y="5792" width="1284" height="724" frameX="0" frameY="0" frameWidth="1284" frameHeight="724" />
<SubTexture name="startup yes0096" x="10272" y="5792" width="1284" height="724" frameX="0" frameY="0" frameWidth="1284" frameHeight="724" />
<SubTexture name="startup yes0097" x="11556" y="5792" width="1284" height="724" frameX="0" frameY="0" frameWidth="1284" frameHeight="724" />
<SubTexture name="startup yes0098" x="12840" y="5792" width="1284" height="724" frameX="0" frameY="0" frameWidth="1284" frameHeight="724" />
<SubTexture name="startup yes0099" x="0" y="6516" width="1284" height="724" frameX="0" frameY="0" frameWidth="1284" frameHeight="724" />
<SubTexture name="startup yes0100" x="1284" y="6516" width="1284" height="724" frameX="0" frameY="0" frameWidth="1284" frameHeight="724" />
<SubTexture name="startup yes0101" x="2568" y="6516" width="1284" height="724" frameX="0" frameY="0" frameWidth="1284" frameHeight="724" />
<SubTexture name="startup yes0102" x="3852" y="6516" width="1284" height="724" frameX="0" frameY="0" frameWidth="1284" frameHeight="724" />
<SubTexture name="startup yes0103" x="5136" y="6516" width="1284" height="724" frameX="0" frameY="0" frameWidth="1284" frameHeight="724" />
<SubTexture name="startup yes0104" x="6420" y="6516" width="1284" height="724" frameX="0" frameY="0" frameWidth="1284" frameHeight="724" />
<SubTexture name="startup yes0105" x="7704" y="6516" width="1284" height="724" frameX="0" frameY="0" frameWidth="1284" frameHeight="724" />
<SubTexture name="startup yes0106" x="8988" y="6516" width="1284" height="724" frameX="0" frameY="0" frameWidth="1284" frameHeight="724" />
<SubTexture name="startup yes0107" x="10272" y="6516" width="1284" height="724" frameX="0" frameY="0" frameWidth="1284" frameHeight="724" />
<SubTexture name="startup yes0108" x="11556" y="6516" width="1284" height="724" frameX="0" frameY="0" frameWidth="1284" frameHeight="724" />
<SubTexture name="startup yes0109" x="12840" y="6516" width="1284" height="724" frameX="0" frameY="0" frameWidth="1284" frameHeight="724" />
<SubTexture name="startup yes0110" x="0" y="7240" width="1284" height="724" frameX="0" frameY="0" frameWidth="1284" frameHeight="724" />
<SubTexture name="startup yes0111" x="1284" y="7240" width="1284" height="724" frameX="0" frameY="0" frameWidth="1284" frameHeight="724" />
<SubTexture name="startup yes0112" x="2568" y="7240" width="1284" height="724" frameX="0" frameY="0" frameWidth="1284" frameHeight="724" />
<SubTexture name="startup yes0113" x="3852" y="7240" width="1284" height="724" frameX="0" frameY="0" frameWidth="1284" frameHeight="724" />
<SubTexture name="startup yes0114" x="5136" y="7240" width="1284" height="724" frameX="0" frameY="0" frameWidth="1284" frameHeight="724" />
<SubTexture name="startup yes0115" x="6420" y="7240" width="1284" height="724" frameX="0" frameY="0" frameWidth="1284" frameHeight="724" />
<SubTexture name="startup yes0116" x="7704" y="7240" width="1284" height="724" frameX="0" frameY="0" frameWidth="1284" frameHeight="724" />
<SubTexture name="startup yes0117" x="8988" y="7240" width="1284" height="724" frameX="0" frameY="0" frameWidth="1284" frameHeight="724" />
<SubTexture name="startup yes0118" x="10272" y="7240" width="1284" height="724" frameX="0" frameY="0" frameWidth="1284" frameHeight="724" />
<SubTexture name="startup yes0119" x="11556" y="7240" width="1284" height="724" frameX="0" frameY="0" frameWidth="1284" frameHeight="724" />
<SubTexture name="startup yes0120" x="12840" y="7240" width="1284" height="724" frameX="0" frameY="0" frameWidth="1284" frameHeight="724" />
</TextureAtlas>
